pyveplot/__init__.py
pyveplot-1.0.2.dist-info/LICENSE
pyveplot-1.0.2.dist-info/METADATA
pyveplot-1.0.2.dist-info/WHEEL
pyveplot-1.0.2.dist-info/top_level.txt
pyveplot-1.0.2.dist-info/RECORD
