Metadata-Version: 2.1
Name: pyveplot
Version: 1.0.2
Summary: SVG Hiveplot Python API
Home-page: http://gitlab.com/rgarcia-herrera/pyveplot
Author: Rodrigo Garcia
Author-email: rgarcia@iecologia.unam.mx
License: GPLv3
Platform: UNKNOWN
Classifier: License :: OSI Approved :: GNU General Public License v3 (GPLv3)
Classifier: Programming Language :: Python :: 3.5
Classifier: Topic :: Scientific/Engineering :: Information Analysis
Classifier: Intended Audience :: Science/Research
Classifier: Topic :: Scientific/Engineering
Requires-Python: >=3.6
Requires-Dist: svgwrite
